firebase_tools_jimmykvick/__init__.py
firebase_tools_jimmykvick/firestore.py
firebase_tools_jimmykvick-0.0.3.dist-info/METADATA
firebase_tools_jimmykvick-0.0.3.dist-info/WHEEL
firebase_tools_jimmykvick-0.0.3.dist-info/licenses/LICENSE
firebase_tools_jimmykvick-0.0.3.dist-info/RECORD
