Metadata-Version: 2.1
Name: firebase_tools_jimmykvick
Version: 0.0.3
Summary: A small example package for common use
Project-URL: Homepage, https://github.com/Serialk89
Project-URL: Bug Tracker, https://github.com/Serialk89
Author-email: Author <jaime.quinones.t@gmail.com>
License-File: LICENSE
Classifier: License :: OSI Approved :: MIT License
Classifier: Operating System :: OS Independent
Classifier: Programming Language :: Python :: 3
Requires-Python: >=3.7
